tuxmate_cli/__init__.py
tuxmate_cli/cli.py
tuxmate_cli/data.py
tuxmate_cli/generator.py
tuxmate_cli-1.1.0.dist-info/METADATA
tuxmate_cli-1.1.0.dist-info/WHEEL
tuxmate_cli-1.1.0.dist-info/entry_points.txt
tuxmate_cli-1.1.0.dist-info/licenses/LICENSE
tuxmate_cli-1.1.0.dist-info/RECORD
