Metadata-Version: 2.4
Name: tuxmate-cli
Version: 1.1.0
Summary: CLI tool for installing Linux packages using tuxmate's curated database
Author-email: Gururagavendra <guruvelu85@gmail.com>
License-File: LICENSE
Keywords: cli,linux,package-manager,tuxmate
Classifier: Development Status :: 3 - Alpha
Classifier: Environment :: Console
Classifier: Intended Audience :: Developers
Classifier: Intended Audience :: System Administrators
Classifier: License :: OSI Approved :: GNU General Public License v3 (GPLv3)
Classifier: Operating System :: POSIX :: Linux
Classifier: Programming Language :: Python :: 3
Classifier: Programming Language :: Python :: 3.10
Classifier: Topic :: System :: Installation/Setup
Classifier: Topic :: System :: Systems Administration
Requires-Python: >=3.10
Requires-Dist: click>=8.1.0
Requires-Dist: dukpy>=0.5.0
Requires-Dist: requests>=2.28.0
Requires-Dist: rich>=13.0.0
